cigsatbuf_utils/__init__.py
cigsatbuf_utils/cig_tool_functions.py
cigsatbuf_utils/DM_files2.py
cigsatbuf_utils/envs.py
cigsatbuf_utils/executables/DMSOILP.EXE
cigsatbuf_utils/executables/DMWEA.EXE
cigsatbuf_utils/helpers.py
cigsatbuf_utils/helpers_gen_file.py
cigsatbuf_utils/helpers_store_file.py
cigsatbuf_utils/make_drainmod_soil_files.py
cigsatbuf_utils/make_drainmod_weather_files.py
cigsatbuf_utils/retrieve_soil_components.py
cigsatbuf_utils/rosetta3/__init__.py
cigsatbuf_utils/rosetta3/ANN_Module.py
cigsatbuf_utils/rosetta3/DB_Module.py
cigsatbuf_utils/rosetta3/inputs_excel_new.xlsx
cigsatbuf_utils/rosetta3/inputs_excel_new_gdb.xlsx
cigsatbuf_utils/rosetta3/inputs_excel_new_y.xlsx
cigsatbuf_utils/rosetta3/Rosetta.sql
cigsatbuf_utils/rosetta3/Rosetta.sqlite
cigsatbuf_utils/rosetta3/Rpredict.py
cigsatbuf_utils/rosetta3/Rpredict_y.py
cigsatbuf_utils/rosetta3/run_Rosetta.sh
cigsatbuf_utils/rosetta3/test_input5.txt
cigsatbuf_utils/samples/daymet_single_location_inputs.txt
cigsatbuf_utils/samples/IA_Benton_summary.xlsx
cigsatbuf_utils/samples/LenaweeCoMI.gen
cigsatbuf_utils-0.1.0.dist-info/METADATA
cigsatbuf_utils-0.1.0.dist-info/WHEEL
cigsatbuf_utils-0.1.0.dist-info/RECORD
