Metadata-Version: 2.1
Name: cigsatbuf-utils
Version: 0.1.0
Summary: 
Author: JK
Author-email: kpodojos@msu.edu
Requires-Python: >=3.11,<4.0
Classifier: Programming Language :: Python :: 3
Classifier: Programming Language :: Python :: 3.11
Classifier: Programming Language :: Python :: 3.12
Classifier: Programming Language :: Python :: 3.13
Requires-Dist: openpyxl (>=3.1.5,<4.0.0)
Requires-Dist: pandas (>=2.2.3,<3.0.0)
Requires-Dist: pyodbc (>=5.2.0,<6.0.0)
